awq_cli/__init__.py
awq_cli/__main__.py
awq_cli/inference.py
awq_cli/quantize.py
awq_cli-0.2.0.dist-info/LICENSE
awq_cli-0.2.0.dist-info/METADATA
awq_cli-0.2.0.dist-info/WHEEL
awq_cli-0.2.0.dist-info/entry_points.txt
awq_cli-0.2.0.dist-info/top_level.txt
awq_cli-0.2.0.dist-info/RECORD
